<?xml version="1.0" encoding="utf-8"?>
<Level>
  <LevelInfo>
    <BPM>130.0</BPM>
    <BeatPerBar>4</BeatPerBar>
    <BeatLen>16</BeatLen>
    <EnterTimeAdjust>415</EnterTimeAdjust>
    <NotePreShow>2.0</NotePreShow>
    <LevelTime>162461</LevelTime>
    <BarAmount>88</BarAmount>
    <BeginBarLen>8</BeginBarLen>
    <IsFourTrack>False</IsFourTrack>
    <TrackCount>5</TrackCount>
    <LevelPreTime>4000</LevelPreTime>
  </LevelInfo>
  <MusicInfo>
    <Title>Kids in the Dark</Title>
    <Artist>All Time Low</Artist>
    <FilePath>audio/bgm/103501</FilePath>
  </MusicInfo>
  <SectionSeq>
    <Section type="previous" endbar="0" mark="" param1="wutai_scene_pre_script_2" />
    <Section type="begin" startbar="1" endbar="8" mark="" param1="wutai_scene_begin_script_2" />
    <Section type="note" startbar="9" endbar="42" mark="" param1="" />
    <Section type="showtime" startbar="43" endbar="46" mark="dance" param1="" />
    <Section type="note" startbar="49" endbar="84" mark="" param1="" />
    <Section type="showtime" startbar="85" endbar="88" mark="pose_xuanku" param1="" />
  </SectionSeq>
  <IndicatorResetPos PosNum="64">
    <Pos Bar="9" BeatPos="0" />
    <Pos Bar="11" BeatPos="0" />
    <Pos Bar="13" BeatPos="0" />
    <Pos Bar="15" BeatPos="0" />
    <Pos Bar="17" BeatPos="0" />
    <Pos Bar="19" BeatPos="0" />
    <Pos Bar="21" BeatPos="0" />
    <Pos Bar="23" BeatPos="0" />
    <Pos Bar="26" BeatPos="0" />
    <Pos Bar="28" BeatPos="24" />
    <Pos Bar="30" BeatPos="32" />
    <Pos Bar="31" BeatPos="32" />
    <Pos Bar="33" BeatPos="24" />
    <Pos Bar="35" BeatPos="0" />
    <Pos Bar="37" BeatPos="8" />
    <Pos Bar="39" BeatPos="0" />
    <Pos Bar="41" BeatPos="24" />
    <Pos Bar="49" BeatPos="0" />
    <Pos Bar="51" BeatPos="0" />
    <Pos Bar="53" BeatPos="0" />
    <Pos Bar="55" BeatPos="0" />
    <Pos Bar="57" BeatPos="0" />
    <Pos Bar="59" BeatPos="0" />
    <Pos Bar="61" BeatPos="0" />
    <Pos Bar="64" BeatPos="24" />
    <Pos Bar="66" BeatPos="24" />
    <Pos Bar="68" BeatPos="32" />
    <Pos Bar="70" BeatPos="24" />
    <Pos Bar="73" BeatPos="0" />
    <Pos Bar="75" BeatPos="8" />
    <Pos Bar="77" BeatPos="0" />
    <Pos Bar="78" BeatPos="24" />
    <Pos Bar="80" BeatPos="32" />
    <Pos Bar="82" BeatPos="32" />
  </IndicatorResetPos>
  <NoteInfo>
    <Normal PosNum="64">
      <Note Bar="9" BeatPos="0" Track="0" Type="0">
        <ScreenPos x="600" y="200">
          <FlyTrack name="波浪形" degree="0.0" />
        </ScreenPos>
      </Note>
      <Note Bar="9" BeatPos="16" Track="0" Type="0">
        <ScreenPos x="-600" y="-200">
          <FlyTrack name="波浪形" degree="158.6626" />
        </ScreenPos>
      </Note>
      <Note Bar="9" BeatPos="24" Track="0" Type="1" EndBar="9" EndPos="40" ID="1">
        <MoveTrack name="长按直线2" degree="0.0" />
        <FlyTrack name="波浪形" degree="184.9489" />
        <ScreenPos x="-600" y="0" />
      </Note>
      <Note Bar="9" BeatPos="48" Track="0" Type="0">
        <ScreenPos x="200" y="-200">
          <FlyTrack name="波浪形" degree="137.9498" />
        </ScreenPos>
      </Note>
      <Note Bar="9" BeatPos="56" Track="0" Type="0">
        <ScreenPos x="200" y="0">
          <FlyTrack name="波浪形" degree="216.5528" />
        </ScreenPos>
      </Note>
      <Note Bar="10" BeatPos="8" Track="0" Type="0">
        <ScreenPos x="-600" y="-100">
          <FlyTrack name="波浪形" degree="113.4309" />
        </ScreenPos>
      </Note>
      <Note Bar="10" BeatPos="16" Track="0" Type="0">
        <ScreenPos x="-400" y="-200">
          <FlyTrack name="波浪形" degree="81.82665" />
        </ScreenPos>
      </Note>
      <Note Bar="10" BeatPos="24" Track="0" Type="1" EndBar="10" EndPos="48" ID="2">
        <MoveTrack name="长按直线1.5" degree="-48.86715" />
        <FlyTrack name="波浪形" degree="53.4501" />
        <ScreenPos x="-200" y="-100" />
      </Note>
      <Note Bar="11" BeatPos="0" Track="0" Type="0">
        <ScreenPos x="600" y="-200">
          <FlyTrack name="波浪形" degree="82.87912" />
        </ScreenPos>
      </Note>
      <Note Bar="11" BeatPos="16" Track="0" Type="0">
        <ScreenPos x="-200" y="200">
          <FlyTrack name="波浪形" degree="343.8021" />
        </ScreenPos>
      </Note>
      <Note Bar="11" BeatPos="24" Track="0" Type="0">
        <ScreenPos x="-200" y="0">
          <FlyTrack name="波浪形" degree="14.5197" />
        </ScreenPos>
      </Note>
      <Note Bar="11" BeatPos="40" Track="0" Type="0">
        <ScreenPos x="600" y="200">
          <FlyTrack name="波浪形" degree="0.0" />
        </ScreenPos>
      </Note>
      <Note Bar="11" BeatPos="56" Track="0" Type="0">
        <ScreenPos x="-600" y="-200">
          <FlyTrack name="波浪形" degree="98.12317" />
        </ScreenPos>
      </Note>
      <Note Bar="12" BeatPos="0" Track="0" Type="0">
        <ScreenPos x="-400" y="-200">
          <FlyTrack name="波浪形" degree="67.95301" />
        </ScreenPos>
      </Note>
      <Note Bar="12" BeatPos="8" Track="0" Type="2" EndBar="12" EndPos="40" ID="3">
        <MoveTrack name="滑动缠绕" degree="151.7015" />
        <FlyTrack name="波浪形" degree="87.13729" />
        <ScreenPos x="600" y="-200" />
      </Note>
      <Note Bar="13" BeatPos="0" Track="0" Type="0">
        <ScreenPos x="-600" y="-200">
          <FlyTrack name="波浪形" degree="180.0" />
        </ScreenPos>
      </Note>
      <Note Bar="13" BeatPos="16" Track="0" Type="0">
        <ScreenPos x="600" y="200">
          <FlyTrack name="波浪形" degree="338.6626" />
        </ScreenPos>
      </Note>
      <Note Bar="13" BeatPos="24" Track="0" Type="1" EndBar="13" EndPos="40" ID="4">
        <MoveTrack name="长按直线2" degree="180.0" />
        <FlyTrack name="波浪形" degree="4.948944" />
        <ScreenPos x="600" y="0" />
      </Note>
      <Note Bar="13" BeatPos="48" Track="0" Type="0">
        <ScreenPos x="-200" y="200">
          <FlyTrack name="波浪形" degree="317.9498" />
        </ScreenPos>
      </Note>
      <Note Bar="13" BeatPos="56" Track="0" Type="0">
        <ScreenPos x="-200" y="0">
          <FlyTrack name="波浪形" degree="36.5528" />
        </ScreenPos>
      </Note>
      <Note Bar="14" BeatPos="8" Track="0" Type="0">
        <ScreenPos x="600" y="100">
          <FlyTrack name="波浪形" degree="293.4309" />
        </ScreenPos>
      </Note>
      <Note Bar="14" BeatPos="16" Track="0" Type="0">
        <ScreenPos x="400" y="200">
          <FlyTrack name="波浪形" degree="261.8267" />
        </ScreenPos>
      </Note>
      <Note Bar="14" BeatPos="24" Track="0" Type="1" EndBar="14" EndPos="48" ID="5">
        <MoveTrack name="长按直线1.5" degree="131.1328" />
        <FlyTrack name="波浪形" degree="233.4501" />
        <ScreenPos x="200" y="100" />
      </Note>
      <Note Bar="15" BeatPos="0" Track="0" Type="0">
        <ScreenPos x="-600" y="200">
          <FlyTrack name="波浪形" degree="262.8791" />
        </ScreenPos>
      </Note>
      <Note Bar="15" BeatPos="16" Track="0" Type="0">
        <ScreenPos x="200" y="-200">
          <FlyTrack name="波浪形" degree="163.8021" />
        </ScreenPos>
      </Note>
      <Note Bar="15" BeatPos="24" Track="0" Type="0">
        <ScreenPos x="200" y="0">
          <FlyTrack name="波浪形" degree="194.5197" />
        </ScreenPos>
      </Note>
      <Note Bar="15" BeatPos="40" Track="0" Type="0">
        <ScreenPos x="-600" y="-200">
          <FlyTrack name="波浪形" degree="180.0" />
        </ScreenPos>
      </Note>
      <Note Bar="15" BeatPos="56" Track="0" Type="0">
        <ScreenPos x="600" y="200">
          <FlyTrack name="波浪形" degree="278.1232" />
        </ScreenPos>
      </Note>
      <Note Bar="16" BeatPos="0" Track="0" Type="0">
        <ScreenPos x="400" y="200">
          <FlyTrack name="波浪形" degree="247.953" />
        </ScreenPos>
      </Note>
      <Note Bar="16" BeatPos="8" Track="0" Type="2" EndBar="16" EndPos="40" ID="6">
        <MoveTrack name="滑动缠绕" degree="331.7015" />
        <FlyTrack name="波浪形" degree="267.1373" />
        <ScreenPos x="-600" y="200" />
      </Note>
      <Note Bar="17" BeatPos="0" Track="0" Type="0">
        <ScreenPos x="600" y="-200">
          <FlyTrack name="波浪形" degree="0.0" />
        </ScreenPos>
      </Note>
      <Note Bar="17" BeatPos="16" Track="0" Type="0">
        <ScreenPos x="-600" y="-200">
          <FlyTrack name="波浪形" degree="85.91408" />
        </ScreenPos>
      </Note>
      <Note Bar="17" BeatPos="24" Track="0" Type="0">
        <ScreenPos x="-400" y="-200">
          <FlyTrack name="波浪形" degree="87.22002" />
        </ScreenPos>
      </Note>
      <Note Bar="17" BeatPos="32" Track="0" Type="1" EndBar="17" EndPos="48" ID="7">
        <MoveTrack name="长按直线2" degree="0.0" />
        <FlyTrack name="波浪形" degree="80.13119" />
        <ScreenPos x="-200" y="-200" />
      </Note>
      <Note Bar="18" BeatPos="0" Track="0" Type="0">
        <ScreenPos x="200" y="200">
          <FlyTrack name="波浪形" degree="171.1347" />
        </ScreenPos>
      </Note>
      <Note Bar="18" BeatPos="16" Track="0" Type="0">
        <ScreenPos x="-600" y="100">
          <FlyTrack name="波浪形" degree="240.641" />
        </ScreenPos>
      </Note>
      <Note Bar="18" BeatPos="24" Track="0" Type="0">
        <ScreenPos x="-400" y="200">
          <FlyTrack name="波浪形" degree="270.6165" />
        </ScreenPos>
      </Note>
      <Note Bar="18" BeatPos="32" Track="0" Type="1" EndBar="18" EndPos="48" ID="8">
        <MoveTrack name="长按直线2" degree="29.21636" />
        <FlyTrack name="波浪形" degree="297.8088" />
        <ScreenPos x="-200" y="100" />
      </Note>
      <Note Bar="19" BeatPos="0" Track="0" Type="0">
        <ScreenPos x="600" y="-200">
          <FlyTrack name="波浪形" degree="82.57188" />
        </ScreenPos>
      </Note>
      <Note Bar="19" BeatPos="16" Track="0" Type="0">
        <ScreenPos x="200" y="-200">
          <FlyTrack name="波浪形" degree="175.4945" />
        </ScreenPos>
      </Note>
      <Note Bar="19" BeatPos="32" Track="0" Type="0">
        <ScreenPos x="-200" y="200">
          <FlyTrack name="波浪形" degree="0.0" />
        </ScreenPos>
      </Note>
      <Note Bar="19" BeatPos="40" Track="0" Type="0">
        <ScreenPos x="-200" y="0">
          <FlyTrack name="波浪形" degree="0.0" />
        </ScreenPos>
      </Note>
      <Note Bar="19" BeatPos="48" Track="0" Type="0">
        <ScreenPos x="-200" y="-200">
          <FlyTrack name="波浪形" degree="0.0" />
        </ScreenPos>
      </Note>
      <Note Bar="20" BeatPos="0" Track="0" Type="2" EndBar="20" EndPos="48" ID="9">
        <MoveTrack name="滑动M型" degree="-1.479095" />
        <FlyTrack name="波浪形" degree="0.0" />
        <ScreenPos x="600" y="200" />
      </Note>
      <Note Bar="21" BeatPos="0" Track="0" Type="0">
        <ScreenPos x="-600" y="200">
          <FlyTrack name="波浪形" degree="171.2655" />
        </ScreenPos>
      </Note>
      <Note Bar="21" BeatPos="16" Track="0" Type="0">
        <ScreenPos x="-300" y="0">
          <FlyTrack name="波浪形" degree="25.91537" />
        </ScreenPos>
      </Note>
      <Note Bar="21" BeatPos="32" Track="0" Type="1" EndBar="21" EndPos="48" ID="10">
        <MoveTrack name="长按直线2" degree="0.0" />
        <FlyTrack name="波浪形" degree="140.1646" />
        <ScreenPos x="-600" y="-200" />
      </Note>
      <Note Bar="22" BeatPos="0" Track="0" Type="0">
        <ScreenPos x="200" y="200">
          <FlyTrack name="波浪形" degree="172.8568" />
        </ScreenPos>
      </Note>
      <Note Bar="22" BeatPos="16" Track="0" Type="0">
        <ScreenPos x="-200" y="-200">
          <FlyTrack name="波浪形" degree="79.37893" />
        </ScreenPos>
      </Note>
      <Note Bar="22" BeatPos="24" Track="0" Type="0">
        <ScreenPos x="-400" y="-200">
          <FlyTrack name="波浪形" degree="86.0148" />
        </ScreenPos>
      </Note>
      <Note Bar="22" BeatPos="32" Track="0" Type="1" EndBar="22" EndPos="48" ID="11">
        <MoveTrack name="长按直线2" degree="-90.6933" />
        <FlyTrack name="波浪形" degree="93.28351" />
        <ScreenPos x="-600" y="-200" />
      </Note>
      <Note Bar="23" BeatPos="0" Track="0" Type="0">
        <ScreenPos x="600" y="-200">
          <FlyTrack name="波浪形" degree="84.80949" />
        </ScreenPos>
      </Note>
      <Note Bar="23" BeatPos="16" Track="0" Type="0">
        <ScreenPos x="300" y="0">
          <FlyTrack name="波浪形" degree="209.8556" />
        </ScreenPos>
      </Note>
      <Note Bar="23" BeatPos="32" Track="0" Type="0">
        <ScreenPos x="0" y="-200">
          <FlyTrack name="波浪形" degree="139.2525" />
        </ScreenPos>
      </Note>
      <Note Bar="23" BeatPos="48" Track="0" Type="0">
        <ScreenPos x="-300" y="0">
          <FlyTrack name="波浪形" degree="206.9945" />
        </ScreenPos>
      </Note>
      <Note Bar="24" BeatPos="0" Track="0" Type="0">
        <ScreenPos x="-600" y="-200">
          <FlyTrack name="波浪形" degree="139.8305" />
        </ScreenPos>
      </Note>
      <Note Bar="24" BeatPos="16" Track="0" Type="0">
        <ScreenPos x="600" y="200">
          <FlyTrack name="波浪形" degree="0.0" />
        </ScreenPos>
      </Note>
      <Note Bar="24" BeatPos="24" Track="0" Type="0">
        <ScreenPos x="600" y="0">
          <FlyTrack name="波浪形" degree="0.0" />
        </ScreenPos>
      </Note>
      <Note Bar="24" BeatPos="32" Track="0" Type="0">
        <ScreenPos x="600" y="-200">
          <FlyTrack name="波浪形" degree="0.0" />
        </ScreenPos>
      </Note>
      <Note Bar="24" BeatPos="48" Track="0" Type="0">
        <ScreenPos x="-600" y="200">
          <FlyTrack name="波浪形" degree="-185.8453" />
        </ScreenPos>
      </Note>
      <Note Bar="25" BeatPos="0" Track="0" Type="1" EndBar="25" EndPos="32" ID="12">
        <MoveTrack name="长按S形" degree="108.1031" />
        <FlyTrack name="波浪形" degree="83.43297" />
        <ScreenPos x="-600" y="-200" />
      </Note>
      <Note Bar="26" BeatPos="0" Track="0" Type="1" EndBar="26" EndPos="16" ID="13">
        <MoveTrack name="长按直线2" degree="90.0186" />
        <FlyTrack name="波浪形" degree="0.0" />
        <ScreenPos x="600" y="200" />
      </Note>
      <Note Bar="26" BeatPos="24" Track="0" Type="0">
        <ScreenPos x="-600" y="-200">
          <FlyTrack name="波浪形" degree="83.48732" />
        </ScreenPos>
      </Note>
      <Note Bar="26" BeatPos="32" Track="0" Type="0">
        <ScreenPos x="-400" y="-200">
          <FlyTrack name="波浪形" degree="87.71285" />
        </ScreenPos>
      </Note>
      <Note Bar="26" BeatPos="40" Track="0" Type="0">
        <ScreenPos x="-200" y="-200">
          <FlyTrack name="波浪形" degree="87.69769" />
        </ScreenPos>
      </Note>
      <Note Bar="26" BeatPos="48" Track="0" Type="0">
        <ScreenPos x="0" y="-200">
          <FlyTrack name="波浪形" degree="84.15498" />
        </ScreenPos>
      </Note>
      <Note Bar="26" BeatPos="56" Track="0" Type="1" EndBar="27" EndPos="8" ID="14">
        <MoveTrack name="长按直线2" degree="179.7026" />
        <FlyTrack name="波浪形" degree="82.87291" />
        <ScreenPos x="600" y="-200" />
      </Note>
      <Note Bar="27" BeatPos="32" Track="0" Type="0">
        <ScreenPos x="-600" y="200">
          <FlyTrack name="波浪形" degree="175.6113" />
        </ScreenPos>
      </Note>
      <Note Bar="27" BeatPos="40" Track="0" Type="0">
        <ScreenPos x="-450" y="50">
          <FlyTrack name="波浪形" degree="165.5901" />
        </ScreenPos>
      </Note>
      <Note Bar="27" BeatPos="48" Track="0" Type="0">
        <ScreenPos x="-300" y="-100">
          <FlyTrack name="波浪形" degree="164.4847" />
        </ScreenPos>
      </Note>
      <Note Bar="27" BeatPos="56" Track="0" Type="1" EndBar="28" EndPos="8" ID="15">
        <MoveTrack name="长按直线2" degree="-179.4856" />
        <FlyTrack name="波浪形" degree="257.762" />
        <ScreenPos x="600" y="200" />
      </Note>
      <Note Bar="28" BeatPos="24" Track="0" Type="0">
        <ScreenPos x="-600" y="-200">
          <FlyTrack name="波浪形" degree="113.4234" />
        </ScreenPos>
      </Note>
      <Note Bar="28" BeatPos="32" Track="0" Type="0">
        <ScreenPos x="-400" y="-200">
          <FlyTrack name="波浪形" degree="61.32563" />
        </ScreenPos>
      </Note>
      <Note Bar="28" BeatPos="48" Track="0" Type="0">
        <ScreenPos x="600" y="-200">
          <FlyTrack name="波浪形" degree="0.0" />
        </ScreenPos>
      </Note>
      <Note Bar="28" BeatPos="56" Track="0" Type="0">
        <ScreenPos x="450" y="-50">
          <FlyTrack name="波浪形" degree="-3.978439" />
        </ScreenPos>
      </Note>
      <Note Bar="29" BeatPos="0" Track="0" Type="1" EndBar="29" EndPos="16" ID="16">
        <MoveTrack name="长按直线2" degree="-178.0603" />
        <FlyTrack name="波浪形" degree="344.625" />
        <ScreenPos x="300" y="100" />
      </Note>
      <Note Bar="29" BeatPos="24" Track="0" Type="0">
        <ScreenPos x="-600" y="200">
          <FlyTrack name="波浪形" degree="248.015" />
        </ScreenPos>
      </Note>
      <Note Bar="29" BeatPos="32" Track="0" Type="0">
        <ScreenPos x="-400" y="200">
          <FlyTrack name="波浪形" degree="277.3246" />
        </ScreenPos>
      </Note>
      <Note Bar="29" BeatPos="40" Track="0" Type="0">
        <ScreenPos x="600" y="200">
          <FlyTrack name="波浪形" degree="345.1188" />
        </ScreenPos>
      </Note>
      <Note Bar="29" BeatPos="48" Track="0" Type="0">
        <ScreenPos x="600" y="0">
          <FlyTrack name="波浪形" degree="12.80865" />
        </ScreenPos>
      </Note>
      <Note Bar="29" BeatPos="56" Track="0" Type="1" EndBar="30" EndPos="16" ID="17">
        <MoveTrack name="长按直线1.5" degree="0.0" />
        <FlyTrack name="波浪形" degree="83.1788" />
        <ScreenPos x="-600" y="-200" />
      </Note>
      <Note Bar="30" BeatPos="32" Track="0" Type="0">
        <ScreenPos x="600" y="200">
          <FlyTrack name="波浪形" degree="263.4873" />
        </ScreenPos>
      </Note>
      <Note Bar="30" BeatPos="40" Track="0" Type="0">
        <ScreenPos x="400" y="200">
          <FlyTrack name="波浪形" degree="267.7129" />
        </ScreenPos>
      </Note>
      <Note Bar="30" BeatPos="48" Track="0" Type="0">
        <ScreenPos x="200" y="200">
          <FlyTrack name="波浪形" degree="264.155" />
        </ScreenPos>
      </Note>
      <Note Bar="30" BeatPos="56" Track="0" Type="0">
        <ScreenPos x="0" y="200">
          <FlyTrack name="波浪形" degree="259.9035" />
        </ScreenPos>
      </Note>
      <Note Bar="31" BeatPos="0" Track="0" Type="1" EndBar="31" EndPos="16" ID="18">
        <MoveTrack name="长按直线2" degree="359.7026" />
        <FlyTrack name="波浪形" degree="262.8729" />
        <ScreenPos x="-600" y="200" />
      </Note>
      <Note Bar="31" BeatPos="32" Track="0" Type="0">
        <ScreenPos x="600" y="-200">
          <FlyTrack name="波浪形" degree="355.6113" />
        </ScreenPos>
      </Note>
      <Note Bar="31" BeatPos="40" Track="0" Type="0">
        <ScreenPos x="450" y="-50">
          <FlyTrack name="波浪形" degree="345.5901" />
        </ScreenPos>
      </Note>
      <Note Bar="31" BeatPos="48" Track="0" Type="0">
        <ScreenPos x="300" y="100">
          <FlyTrack name="波浪形" degree="344.4847" />
        </ScreenPos>
      </Note>
      <Note Bar="31" BeatPos="56" Track="0" Type="1" EndBar="32" EndPos="8" ID="19">
        <MoveTrack name="长按直线2" degree="0.5144348" />
        <FlyTrack name="波浪形" degree="77.76196" />
        <ScreenPos x="-600" y="-200" />
      </Note>
      <Note Bar="32" BeatPos="24" Track="0" Type="0">
        <ScreenPos x="600" y="200">
          <FlyTrack name="波浪形" degree="293.4234" />
        </ScreenPos>
      </Note>
      <Note Bar="32" BeatPos="32" Track="0" Type="0">
        <ScreenPos x="400" y="200">
          <FlyTrack name="波浪形" degree="241.3256" />
        </ScreenPos>
      </Note>
      <Note Bar="32" BeatPos="48" Track="0" Type="0">
        <ScreenPos x="-600" y="200">
          <FlyTrack name="波浪形" degree="180.0" />
        </ScreenPos>
      </Note>
      <Note Bar="32" BeatPos="56" Track="0" Type="0">
        <ScreenPos x="-450" y="50">
          <FlyTrack name="波浪形" degree="176.0216" />
        </ScreenPos>
      </Note>
      <Note Bar="33" BeatPos="0" Track="0" Type="1" EndBar="33" EndPos="16" ID="20">
        <MoveTrack name="长按直线2" degree="1.939682" />
        <FlyTrack name="波浪形" degree="164.625" />
        <ScreenPos x="-300" y="-100" />
      </Note>
      <Note Bar="33" BeatPos="24" Track="0" Type="0">
        <ScreenPos x="600" y="-200">
          <FlyTrack name="波浪形" degree="68.01498" />
        </ScreenPos>
      </Note>
      <Note Bar="33" BeatPos="32" Track="0" Type="0">
        <ScreenPos x="400" y="-200">
          <FlyTrack name="波浪形" degree="97.32458" />
        </ScreenPos>
      </Note>
      <Note Bar="33" BeatPos="40" Track="0" Type="0">
        <ScreenPos x="-600" y="-200">
          <FlyTrack name="波浪形" degree="165.1188" />
        </ScreenPos>
      </Note>
      <Note Bar="33" BeatPos="48" Track="0" Type="0">
        <ScreenPos x="-600" y="0">
          <FlyTrack name="波浪形" degree="192.8087" />
        </ScreenPos>
      </Note>
      <Note Bar="34" BeatPos="0" Track="0" Type="0">
        <ScreenPos x="200" y="200">
          <FlyTrack name="波浪形" degree="0.0" />
        </ScreenPos>
      </Note>
      <Note Bar="34" BeatPos="16" Track="0" Type="0">
        <ScreenPos x="200" y="-200">
          <FlyTrack name="波浪形" degree="84.67587" />
        </ScreenPos>
      </Note>
      <Note Bar="34" BeatPos="32" Track="0" Type="0">
        <ScreenPos x="600" y="-200">
          <FlyTrack name="波浪形" degree="-3.434402" />
        </ScreenPos>
      </Note>
      <Note Bar="34" BeatPos="48" Track="0" Type="1" EndBar="35" EndPos="0" ID="21">
        <MoveTrack name="长按直线2" degree="-179.3107" />
        <FlyTrack name="波浪形" degree="260.1216" />
        <ScreenPos x="600" y="200" />
      </Note>
      <Note Bar="35" BeatPos="0" Track="0" Type="0">
        <ScreenPos x="-300" y="200">
          <FlyTrack name="波浪形" degree="170.2052" />
        </ScreenPos>
      </Note>
      <Note Bar="35" BeatPos="16" Track="0" Type="0">
        <ScreenPos x="-600" y="0">
          <FlyTrack name="波浪形" degree="140.5964" />
        </ScreenPos>
      </Note>
      <Note Bar="35" BeatPos="32" Track="0" Type="0">
        <ScreenPos x="-300" y="-200">
          <FlyTrack name="波浪形" degree="27.17424" />
        </ScreenPos>
      </Note>
      <Note Bar="35" BeatPos="48" Track="0" Type="1" EndBar="36" EndPos="0" ID="22">
        <MoveTrack name="长按直线2" degree="0.5016251" />
        <FlyTrack name="波浪形" degree="324.2307" />
        <ScreenPos x="0" y="0" />
      </Note>
      <Note Bar="36" BeatPos="16" Track="0" Type="0">
        <ScreenPos x="600" y="200">
          <FlyTrack name="波浪形" degree="-2.367035" />
        </ScreenPos>
      </Note>
      <Note Bar="36" BeatPos="32" Track="0" Type="1" EndBar="36" EndPos="48" ID="23">
        <MoveTrack name="长按直线2" degree="-179.561" />
        <FlyTrack name="波浪形" degree="84.12939" />
        <ScreenPos x="600" y="-200" />
      </Note>
      <Note Bar="37" BeatPos="8" Track="0" Type="0">
        <ScreenPos x="-200" y="200">
          <FlyTrack name="波浪形" degree="346.6088" />
        </ScreenPos>
      </Note>
      <Note Bar="37" BeatPos="16" Track="0" Type="0">
        <ScreenPos x="-200" y="0">
          <FlyTrack name="波浪形" degree="15.52046" />
        </ScreenPos>
      </Note>
      <Note Bar="37" BeatPos="32" Track="0" Type="0">
        <ScreenPos x="200" y="-200">
          <FlyTrack name="波浪形" degree="86.24101" />
        </ScreenPos>
      </Note>
      <Note Bar="37" BeatPos="48" Track="0" Type="1" EndBar="38" EndPos="0" ID="24">
        <MoveTrack name="长按直线2" degree="-89.66404" />
        <FlyTrack name="波浪形" degree="-3.653366" />
        <ScreenPos x="600" y="-200" />
      </Note>
      <Note Bar="38" BeatPos="8" Track="0" Type="0">
        <ScreenPos x="-600" y="-200">
          <FlyTrack name="波浪形" degree="81.84164" />
        </ScreenPos>
      </Note>
      <Note Bar="38" BeatPos="24" Track="0" Type="0">
        <ScreenPos x="200" y="200">
          <FlyTrack name="波浪形" degree="203.6496" />
        </ScreenPos>
      </Note>
      <Note Bar="38" BeatPos="32" Track="0" Type="0">
        <ScreenPos x="200" y="0">
          <FlyTrack name="波浪形" degree="137.1682" />
        </ScreenPos>
      </Note>
      <Note Bar="38" BeatPos="48" Track="0" Type="0">
        <ScreenPos x="-600" y="200">
          <FlyTrack name="波浪形" degree="264.6406" />
        </ScreenPos>
      </Note>
      <Note Bar="39" BeatPos="0" Track="0" Type="1" EndBar="39" EndPos="16" ID="25">
        <MoveTrack name="长按直线2" degree="179.7026" />
        <FlyTrack name="波浪形" degree="82.87291" />
        <ScreenPos x="600" y="-200" />
      </Note>
      <Note Bar="39" BeatPos="32" Track="0" Type="0">
        <ScreenPos x="-600" y="200">
          <FlyTrack name="波浪形" degree="175.6113" />
        </ScreenPos>
      </Note>
      <Note Bar="39" BeatPos="40" Track="0" Type="0">
        <ScreenPos x="-450" y="50">
          <FlyTrack name="波浪形" degree="165.5901" />
        </ScreenPos>
      </Note>
      <Note Bar="39" BeatPos="48" Track="0" Type="0">
        <ScreenPos x="-300" y="-100">
          <FlyTrack name="波浪形" degree="164.4847" />
        </ScreenPos>
      </Note>
      <Note Bar="39" BeatPos="56" Track="0" Type="1" EndBar="40" EndPos="8" ID="26">
        <MoveTrack name="长按直线2" degree="-179.4856" />
        <FlyTrack name="波浪形" degree="257.762" />
        <ScreenPos x="600" y="200" />
      </Note>
      <Note Bar="40" BeatPos="24" Track="0" Type="0">
        <ScreenPos x="-600" y="-200">
          <FlyTrack name="波浪形" degree="113.4234" />
        </ScreenPos>
      </Note>
      <Note Bar="40" BeatPos="32" Track="0" Type="0">
        <ScreenPos x="-400" y="-200">
          <FlyTrack name="波浪形" degree="61.32563" />
        </ScreenPos>
      </Note>
      <Note Bar="40" BeatPos="48" Track="0" Type="0">
        <ScreenPos x="600" y="-200">
          <FlyTrack name="波浪形" degree="0.0" />
        </ScreenPos>
      </Note>
      <Note Bar="40" BeatPos="56" Track="0" Type="0">
        <ScreenPos x="450" y="-50">
          <FlyTrack name="波浪形" degree="-3.978439" />
        </ScreenPos>
      </Note>
      <Note Bar="41" BeatPos="0" Track="0" Type="1" EndBar="41" EndPos="16" ID="27">
        <MoveTrack name="长按直线2" degree="-178.0603" />
        <FlyTrack name="波浪形" degree="344.625" />
        <ScreenPos x="300" y="100" />
      </Note>
      <Note Bar="41" BeatPos="24" Track="0" Type="0">
        <ScreenPos x="-600" y="200">
          <FlyTrack name="波浪形" degree="248.015" />
        </ScreenPos>
      </Note>
      <Note Bar="41" BeatPos="32" Track="0" Type="0">
        <ScreenPos x="-400" y="200">
          <FlyTrack name="波浪形" degree="277.3246" />
        </ScreenPos>
      </Note>
      <Note Bar="41" BeatPos="40" Track="0" Type="0">
        <ScreenPos x="600" y="200">
          <FlyTrack name="波浪形" degree="345.1188" />
        </ScreenPos>
      </Note>
      <Note Bar="41" BeatPos="48" Track="0" Type="0">
        <ScreenPos x="600" y="0">
          <FlyTrack name="波浪形" degree="12.80865" />
        </ScreenPos>
      </Note>
      <Note Bar="41" BeatPos="56" Track="0" Type="1" EndBar="42" EndPos="16" ID="28">
        <MoveTrack name="长按直线1.5" degree="0.0" />
        <FlyTrack name="波浪形" degree="83.1788" />
        <ScreenPos x="-600" y="-200" />
      </Note>
      <Note Bar="42" BeatPos="32" Track="0" Type="0">
        <ScreenPos x="600" y="200">
          <FlyTrack name="波浪形" degree="263.4873" />
        </ScreenPos>
      </Note>
      <Note Bar="42" BeatPos="40" Track="0" Type="0">
        <ScreenPos x="400" y="200">
          <FlyTrack name="波浪形" degree="267.7129" />
        </ScreenPos>
      </Note>
      <Note Bar="42" BeatPos="48" Track="0" Type="0">
        <ScreenPos x="200" y="200">
          <FlyTrack name="波浪形" degree="264.155" />
        </ScreenPos>
      </Note>
      <Note Bar="49" BeatPos="0" Track="4" Type="0">
        <ScreenPos x="-600" y="200">
          <FlyTrack name="波浪形" degree="262.8791" />
        </ScreenPos>
      </Note>
      <Note Bar="49" BeatPos="16" Track="4" Type="0">
        <ScreenPos x="200" y="-200">
          <FlyTrack name="波浪形" degree="163.8021" />
        </ScreenPos>
      </Note>
      <Note Bar="49" BeatPos="24" Track="4" Type="0">
        <ScreenPos x="200" y="0">
          <FlyTrack name="波浪形" degree="194.5197" />
        </ScreenPos>
      </Note>
      <Note Bar="49" BeatPos="40" Track="4" Type="0">
        <ScreenPos x="-600" y="-200">
          <FlyTrack name="波浪形" degree="180.0" />
        </ScreenPos>
      </Note>
      <Note Bar="49" BeatPos="56" Track="4" Type="0">
        <ScreenPos x="600" y="200">
          <FlyTrack name="波浪形" degree="278.1232" />
        </ScreenPos>
      </Note>
      <Note Bar="50" BeatPos="0" Track="4" Type="0">
        <ScreenPos x="400" y="200">
          <FlyTrack name="波浪形" degree="247.953" />
        </ScreenPos>
      </Note>
      <Note Bar="50" BeatPos="8" Track="4" Type="2" EndBar="50" EndPos="40" ID="29">
        <MoveTrack name="滑动缠绕" degree="331.7015" />
        <FlyTrack name="波浪形" degree="267.1373" />
        <ScreenPos x="-600" y="200" />
      </Note>
      <Note Bar="51" BeatPos="0" Track="4" Type="0">
        <ScreenPos x="600" y="200">
          <FlyTrack name="波浪形" degree="360.0" />
        </ScreenPos>
      </Note>
      <Note Bar="51" BeatPos="16" Track="4" Type="0">
        <ScreenPos x="-600" y="-200">
          <FlyTrack name="波浪形" degree="158.6626" />
        </ScreenPos>
      </Note>
      <Note Bar="51" BeatPos="24" Track="4" Type="1" EndBar="51" EndPos="40" ID="30">
        <MoveTrack name="长按直线2" degree="360.0" />
        <FlyTrack name="波浪形" degree="184.949" />
        <ScreenPos x="-600" y="0" />
      </Note>
      <Note Bar="51" BeatPos="48" Track="4" Type="0">
        <ScreenPos x="200" y="-200">
          <FlyTrack name="波浪形" degree="137.9498" />
        </ScreenPos>
      </Note>
      <Note Bar="51" BeatPos="56" Track="4" Type="0">
        <ScreenPos x="200" y="0">
          <FlyTrack name="波浪形" degree="216.5528" />
        </ScreenPos>
      </Note>
      <Note Bar="52" BeatPos="8" Track="4" Type="0">
        <ScreenPos x="-600" y="-100">
          <FlyTrack name="波浪形" degree="113.4309" />
        </ScreenPos>
      </Note>
      <Note Bar="52" BeatPos="16" Track="4" Type="0">
        <ScreenPos x="-400" y="-200">
          <FlyTrack name="波浪形" degree="81.82666" />
        </ScreenPos>
      </Note>
      <Note Bar="52" BeatPos="24" Track="4" Type="1" EndBar="52" EndPos="48" ID="31">
        <MoveTrack name="长按直线1.5" degree="311.1328" />
        <FlyTrack name="波浪形" degree="53.4501" />
        <ScreenPos x="-200" y="-100" />
      </Note>
      <Note Bar="53" BeatPos="0" Track="4" Type="0">
        <ScreenPos x="600" y="-200">
          <FlyTrack name="波浪形" degree="82.87912" />
        </ScreenPos>
      </Note>
      <Note Bar="53" BeatPos="16" Track="4" Type="0">
        <ScreenPos x="-200" y="200">
          <FlyTrack name="波浪形" degree="343.8021" />
        </ScreenPos>
      </Note>
      <Note Bar="53" BeatPos="24" Track="4" Type="0">
        <ScreenPos x="-200" y="0">
          <FlyTrack name="波浪形" degree="14.51971" />
        </ScreenPos>
      </Note>
      <Note Bar="53" BeatPos="40" Track="4" Type="0">
        <ScreenPos x="600" y="200">
          <FlyTrack name="波浪形" degree="360.0" />
        </ScreenPos>
      </Note>
      <Note Bar="53" BeatPos="56" Track="4" Type="0">
        <ScreenPos x="-600" y="-200">
          <FlyTrack name="波浪形" degree="98.12317" />
        </ScreenPos>
      </Note>
      <Note Bar="54" BeatPos="0" Track="4" Type="0">
        <ScreenPos x="-400" y="-200">
          <FlyTrack name="波浪形" degree="67.953" />
        </ScreenPos>
      </Note>
      <Note Bar="54" BeatPos="8" Track="4" Type="2" EndBar="54" EndPos="40" ID="32">
        <MoveTrack name="滑动缠绕" degree="151.7015" />
        <FlyTrack name="波浪形" degree="87.1373" />
        <ScreenPos x="600" y="-200" />
      </Note>
      <Note Bar="55" BeatPos="0" Track="4" Type="0">
        <ScreenPos x="-600" y="200">
          <FlyTrack name="波浪形" degree="180.0" />
        </ScreenPos>
      </Note>
      <Note Bar="55" BeatPos="16" Track="4" Type="0">
        <ScreenPos x="600" y="200">
          <FlyTrack name="波浪形" degree="265.9141" />
        </ScreenPos>
      </Note>
      <Note Bar="55" BeatPos="24" Track="4" Type="0">
        <ScreenPos x="400" y="200">
          <FlyTrack name="波浪形" degree="267.22" />
        </ScreenPos>
      </Note>
      <Note Bar="55" BeatPos="32" Track="4" Type="1" EndBar="55" EndPos="48" ID="33">
        <MoveTrack name="长按直线2" degree="180.0" />
        <FlyTrack name="波浪形" degree="260.1312" />
        <ScreenPos x="200" y="200" />
      </Note>
      <Note Bar="56" BeatPos="0" Track="4" Type="0">
        <ScreenPos x="-200" y="-200">
          <FlyTrack name="波浪形" degree="351.1347" />
        </ScreenPos>
      </Note>
      <Note Bar="56" BeatPos="16" Track="4" Type="0">
        <ScreenPos x="600" y="-100">
          <FlyTrack name="波浪形" degree="60.64099" />
        </ScreenPos>
      </Note>
      <Note Bar="56" BeatPos="24" Track="4" Type="0">
        <ScreenPos x="400" y="-200">
          <FlyTrack name="波浪形" degree="90.61652" />
        </ScreenPos>
      </Note>
      <Note Bar="56" BeatPos="32" Track="4" Type="1" EndBar="56" EndPos="48" ID="34">
        <MoveTrack name="长按直线2" degree="209.2164" />
        <FlyTrack name="波浪形" degree="117.8088" />
        <ScreenPos x="200" y="-100" />
      </Note>
      <Note Bar="57" BeatPos="0" Track="4" Type="0">
        <ScreenPos x="-600" y="200">
          <FlyTrack name="波浪形" degree="262.5719" />
        </ScreenPos>
      </Note>
      <Note Bar="57" BeatPos="16" Track="4" Type="0">
        <ScreenPos x="-200" y="200">
          <FlyTrack name="波浪形" degree="355.4945" />
        </ScreenPos>
      </Note>
      <Note Bar="57" BeatPos="32" Track="4" Type="0">
        <ScreenPos x="200" y="-200">
          <FlyTrack name="波浪形" degree="180.0" />
        </ScreenPos>
      </Note>
      <Note Bar="57" BeatPos="40" Track="4" Type="0">
        <ScreenPos x="200" y="0">
          <FlyTrack name="波浪形" degree="180.0" />
        </ScreenPos>
      </Note>
      <Note Bar="57" BeatPos="48" Track="4" Type="0">
        <ScreenPos x="200" y="200">
          <FlyTrack name="波浪形" degree="180.0" />
        </ScreenPos>
      </Note>
      <Note Bar="58" BeatPos="0" Track="4" Type="2" EndBar="58" EndPos="48" ID="35">
        <MoveTrack name="滑动M型" degree="178.5209" />
        <FlyTrack name="波浪形" degree="180.0" />
        <ScreenPos x="-600" y="-200" />
      </Note>
      <Note Bar="59" BeatPos="0" Track="4" Type="0">
        <ScreenPos x="600" y="-200">
          <FlyTrack name="波浪形" degree="351.2656" />
        </ScreenPos>
      </Note>
      <Note Bar="59" BeatPos="16" Track="4" Type="0">
        <ScreenPos x="300" y="0">
          <FlyTrack name="波浪形" degree="205.9154" />
        </ScreenPos>
      </Note>
      <Note Bar="59" BeatPos="32" Track="4" Type="1" EndBar="59" EndPos="48" ID="36">
        <MoveTrack name="长按直线2" degree="180.0" />
        <FlyTrack name="波浪形" degree="320.1646" />
        <ScreenPos x="600" y="200" />
      </Note>
      <Note Bar="60" BeatPos="0" Track="4" Type="0">
        <ScreenPos x="-200" y="-200">
          <FlyTrack name="波浪形" degree="352.8568" />
        </ScreenPos>
      </Note>
      <Note Bar="60" BeatPos="16" Track="4" Type="0">
        <ScreenPos x="200" y="200">
          <FlyTrack name="波浪形" degree="259.3789" />
        </ScreenPos>
      </Note>
      <Note Bar="60" BeatPos="24" Track="4" Type="0">
        <ScreenPos x="400" y="200">
          <FlyTrack name="波浪形" degree="266.0148" />
        </ScreenPos>
      </Note>
      <Note Bar="60" BeatPos="32" Track="4" Type="1" EndBar="60" EndPos="48" ID="37">
        <MoveTrack name="长按直线2" degree="89.3067" />
        <FlyTrack name="波浪形" degree="273.2835" />
        <ScreenPos x="600" y="200" />
      </Note>
      <Note Bar="61" BeatPos="0" Track="4" Type="0">
        <ScreenPos x="-600" y="200">
          <FlyTrack name="波浪形" degree="264.8095" />
        </ScreenPos>
      </Note>
      <Note Bar="61" BeatPos="16" Track="4" Type="0">
        <ScreenPos x="-300" y="0">
          <FlyTrack name="波浪形" degree="29.85565" />
        </ScreenPos>
      </Note>
      <Note Bar="61" BeatPos="32" Track="4" Type="0">
        <ScreenPos x="0" y="200">
          <FlyTrack name="波浪形" degree="319.2525" />
        </ScreenPos>
      </Note>
      <Note Bar="61" BeatPos="48" Track="4" Type="0">
        <ScreenPos x="300" y="0">
          <FlyTrack name="波浪形" degree="26.99451" />
        </ScreenPos>
      </Note>
      <Note Bar="62" BeatPos="0" Track="4" Type="0">
        <ScreenPos x="600" y="200">
          <FlyTrack name="波浪形" degree="319.8305" />
        </ScreenPos>
      </Note>
      <Note Bar="62" BeatPos="16" Track="4" Type="0">
        <ScreenPos x="-600" y="-200">
          <FlyTrack name="波浪形" degree="180.0" />
        </ScreenPos>
      </Note>
      <Note Bar="62" BeatPos="24" Track="4" Type="0">
        <ScreenPos x="-600" y="0">
          <FlyTrack name="波浪形" degree="180.0" />
        </ScreenPos>
      </Note>
      <Note Bar="62" BeatPos="32" Track="4" Type="0">
        <ScreenPos x="-600" y="200">
          <FlyTrack name="波浪形" degree="180.0" />
        </ScreenPos>
      </Note>
      <Note Bar="62" BeatPos="48" Track="4" Type="0">
        <ScreenPos x="600" y="-200">
          <FlyTrack name="波浪形" degree="-5.845276" />
        </ScreenPos>
      </Note>
      <Note Bar="63" BeatPos="0" Track="4" Type="1" EndBar="63" EndPos="32" ID="38">
        <MoveTrack name="长按S形" degree="288.1031" />
        <FlyTrack name="波浪形" degree="263.433" />
        <ScreenPos x="600" y="200" />
      </Note>
      <Note Bar="64" BeatPos="0" Track="4" Type="1" EndBar="64" EndPos="16" ID="39">
        <MoveTrack name="长按直线2" degree="270.0186" />
        <FlyTrack name="波浪形" degree="180.0" />
        <ScreenPos x="-600" y="-200" />
      </Note>
      <Note Bar="64" BeatPos="24" Track="4" Type="0">
        <ScreenPos x="600" y="200">
          <FlyTrack name="波浪形" degree="263.4873" />
        </ScreenPos>
      </Note>
      <Note Bar="64" BeatPos="32" Track="4" Type="0">
        <ScreenPos x="400" y="200">
          <FlyTrack name="波浪形" degree="267.7129" />
        </ScreenPos>
      </Note>
      <Note Bar="64" BeatPos="40" Track="4" Type="0">
        <ScreenPos x="200" y="200">
          <FlyTrack name="波浪形" degree="267.6977" />
        </ScreenPos>
      </Note>
      <Note Bar="64" BeatPos="48" Track="4" Type="0">
        <ScreenPos x="0" y="200">
          <FlyTrack name="波浪形" degree="264.155" />
        </ScreenPos>
      </Note>
      <Note Bar="64" BeatPos="56" Track="4" Type="1" EndBar="65" EndPos="8" ID="40">
        <MoveTrack name="长按直线2" degree="359.7026" />
        <FlyTrack name="波浪形" degree="262.8729" />
        <ScreenPos x="-600" y="200" />
      </Note>
      <Note Bar="65" BeatPos="32" Track="4" Type="0">
        <ScreenPos x="600" y="-200">
          <FlyTrack name="波浪形" degree="355.6113" />
        </ScreenPos>
      </Note>
      <Note Bar="65" BeatPos="40" Track="4" Type="0">
        <ScreenPos x="450" y="-50">
          <FlyTrack name="波浪形" degree="345.5901" />
        </ScreenPos>
      </Note>
      <Note Bar="65" BeatPos="48" Track="4" Type="0">
        <ScreenPos x="300" y="100">
          <FlyTrack name="波浪形" degree="344.4847" />
        </ScreenPos>
      </Note>
      <Note Bar="65" BeatPos="56" Track="4" Type="1" EndBar="66" EndPos="8" ID="41">
        <MoveTrack name="长按直线2" degree="0.5144348" />
        <FlyTrack name="波浪形" degree="77.76196" />
        <ScreenPos x="-600" y="-200" />
      </Note>
      <Note Bar="66" BeatPos="24" Track="4" Type="0">
        <ScreenPos x="600" y="200">
          <FlyTrack name="波浪形" degree="293.4234" />
        </ScreenPos>
      </Note>
      <Note Bar="66" BeatPos="32" Track="4" Type="0">
        <ScreenPos x="400" y="200">
          <FlyTrack name="波浪形" degree="241.3256" />
        </ScreenPos>
      </Note>
      <Note Bar="66" BeatPos="48" Track="4" Type="0">
        <ScreenPos x="-600" y="200">
          <FlyTrack name="波浪形" degree="180.0" />
        </ScreenPos>
      </Note>
      <Note Bar="66" BeatPos="56" Track="4" Type="0">
        <ScreenPos x="-450" y="50">
          <FlyTrack name="波浪形" degree="176.0216" />
        </ScreenPos>
      </Note>
      <Note Bar="67" BeatPos="0" Track="4" Type="1" EndBar="67" EndPos="16" ID="42">
        <MoveTrack name="长按直线2" degree="1.939682" />
        <FlyTrack name="波浪形" degree="164.625" />
        <ScreenPos x="-300" y="-100" />
      </Note>
      <Note Bar="67" BeatPos="24" Track="4" Type="0">
        <ScreenPos x="600" y="-200">
          <FlyTrack name="波浪形" degree="68.01498" />
        </ScreenPos>
      </Note>
      <Note Bar="67" BeatPos="32" Track="4" Type="0">
        <ScreenPos x="400" y="-200">
          <FlyTrack name="波浪形" degree="97.32458" />
        </ScreenPos>
      </Note>
      <Note Bar="67" BeatPos="40" Track="4" Type="0">
        <ScreenPos x="-600" y="-200">
          <FlyTrack name="波浪形" degree="165.1188" />
        </ScreenPos>
      </Note>
      <Note Bar="67" BeatPos="48" Track="4" Type="0">
        <ScreenPos x="-600" y="0">
          <FlyTrack name="波浪形" degree="192.8087" />
        </ScreenPos>
      </Note>
      <Note Bar="67" BeatPos="56" Track="4" Type="1" EndBar="68" EndPos="16" ID="43">
        <MoveTrack name="长按直线1.5" degree="180.0" />
        <FlyTrack name="波浪形" degree="263.1788" />
        <ScreenPos x="600" y="200" />
      </Note>
      <Note Bar="68" BeatPos="32" Track="4" Type="0">
        <ScreenPos x="-600" y="-200">
          <FlyTrack name="波浪形" degree="83.4873" />
        </ScreenPos>
      </Note>
      <Note Bar="68" BeatPos="40" Track="4" Type="0">
        <ScreenPos x="-400" y="-200">
          <FlyTrack name="波浪形" degree="87.71286" />
        </ScreenPos>
      </Note>
      <Note Bar="68" BeatPos="48" Track="4" Type="0">
        <ScreenPos x="-200" y="-200">
          <FlyTrack name="波浪形" degree="84.15497" />
        </ScreenPos>
      </Note>
      <Note Bar="68" BeatPos="56" Track="4" Type="0">
        <ScreenPos x="0" y="-200">
          <FlyTrack name="波浪形" degree="79.9035" />
        </ScreenPos>
      </Note>
      <Note Bar="69" BeatPos="0" Track="4" Type="1" EndBar="69" EndPos="16" ID="44">
        <MoveTrack name="长按直线2" degree="179.7026" />
        <FlyTrack name="波浪形" degree="82.87292" />
        <ScreenPos x="600" y="-200" />
      </Note>
      <Note Bar="69" BeatPos="32" Track="4" Type="0">
        <ScreenPos x="-600" y="200">
          <FlyTrack name="波浪形" degree="175.6113" />
        </ScreenPos>
      </Note>
      <Note Bar="69" BeatPos="40" Track="4" Type="0">
        <ScreenPos x="-450" y="50">
          <FlyTrack name="波浪形" degree="165.5901" />
        </ScreenPos>
      </Note>
      <Note Bar="69" BeatPos="48" Track="4" Type="0">
        <ScreenPos x="-300" y="-100">
          <FlyTrack name="波浪形" degree="164.4847" />
        </ScreenPos>
      </Note>
      <Note Bar="69" BeatPos="56" Track="4" Type="1" EndBar="70" EndPos="8" ID="45">
        <MoveTrack name="长按直线2" degree="180.5144" />
        <FlyTrack name="波浪形" degree="257.762" />
        <ScreenPos x="600" y="200" />
      </Note>
      <Note Bar="70" BeatPos="24" Track="4" Type="0">
        <ScreenPos x="-600" y="-200">
          <FlyTrack name="波浪形" degree="113.4234" />
        </ScreenPos>
      </Note>
      <Note Bar="70" BeatPos="32" Track="4" Type="0">
        <ScreenPos x="-400" y="-200">
          <FlyTrack name="波浪形" degree="61.32562" />
        </ScreenPos>
      </Note>
      <Note Bar="70" BeatPos="48" Track="4" Type="0">
        <ScreenPos x="600" y="-200">
          <FlyTrack name="波浪形" degree="360.0" />
        </ScreenPos>
      </Note>
      <Note Bar="70" BeatPos="56" Track="4" Type="0">
        <ScreenPos x="450" y="-50">
          <FlyTrack name="波浪形" degree="356.0215" />
        </ScreenPos>
      </Note>
      <Note Bar="71" BeatPos="0" Track="4" Type="1" EndBar="71" EndPos="16" ID="46">
        <MoveTrack name="长按直线2" degree="181.9397" />
        <FlyTrack name="波浪形" degree="344.625" />
        <ScreenPos x="300" y="100" />
      </Note>
      <Note Bar="71" BeatPos="24" Track="4" Type="0">
        <ScreenPos x="-600" y="200">
          <FlyTrack name="波浪形" degree="248.015" />
        </ScreenPos>
      </Note>
      <Note Bar="71" BeatPos="32" Track="4" Type="0">
        <ScreenPos x="-400" y="200">
          <FlyTrack name="波浪形" degree="277.3246" />
        </ScreenPos>
      </Note>
      <Note Bar="71" BeatPos="40" Track="4" Type="0">
        <ScreenPos x="600" y="200">
          <FlyTrack name="波浪形" degree="345.1188" />
        </ScreenPos>
      </Note>
      <Note Bar="71" BeatPos="48" Track="4" Type="0">
        <ScreenPos x="600" y="0">
          <FlyTrack name="波浪形" degree="12.80865" />
        </ScreenPos>
      </Note>
      <Note Bar="72" BeatPos="0" Track="4" Type="0">
        <ScreenPos x="-200" y="-200">
          <FlyTrack name="波浪形" degree="180.0" />
        </ScreenPos>
      </Note>
      <Note Bar="72" BeatPos="16" Track="4" Type="0">
        <ScreenPos x="-200" y="200">
          <FlyTrack name="波浪形" degree="264.6759" />
        </ScreenPos>
      </Note>
      <Note Bar="72" BeatPos="32" Track="4" Type="0">
        <ScreenPos x="-600" y="200">
          <FlyTrack name="波浪形" degree="176.5656" />
        </ScreenPos>
      </Note>
      <Note Bar="72" BeatPos="48" Track="4" Type="1" EndBar="73" EndPos="0" ID="47">
        <MoveTrack name="长按直线2" degree="0.6893311" />
        <FlyTrack name="波浪形" degree="80.12164" />
        <ScreenPos x="-600" y="-200" />
      </Note>
      <Note Bar="73" BeatPos="0" Track="4" Type="0">
        <ScreenPos x="300" y="-200">
          <FlyTrack name="波浪形" degree="350.2052" />
        </ScreenPos>
      </Note>
      <Note Bar="73" BeatPos="16" Track="4" Type="0">
        <ScreenPos x="600" y="0">
          <FlyTrack name="波浪形" degree="320.5964" />
        </ScreenPos>
      </Note>
      <Note Bar="73" BeatPos="32" Track="4" Type="0">
        <ScreenPos x="300" y="200">
          <FlyTrack name="波浪形" degree="207.1742" />
        </ScreenPos>
      </Note>
      <Note Bar="73" BeatPos="48" Track="4" Type="1" EndBar="74" EndPos="0" ID="48">
        <MoveTrack name="长按直线2" degree="180.5016" />
        <FlyTrack name="波浪形" degree="144.2307" />
        <ScreenPos x="0" y="0" />
      </Note>
      <Note Bar="74" BeatPos="16" Track="4" Type="0">
        <ScreenPos x="-600" y="-200">
          <FlyTrack name="波浪形" degree="177.633" />
        </ScreenPos>
      </Note>
      <Note Bar="74" BeatPos="32" Track="4" Type="1" EndBar="74" EndPos="48" ID="49">
        <MoveTrack name="长按直线2" degree="0.4390411" />
        <FlyTrack name="波浪形" degree="264.1294" />
        <ScreenPos x="-600" y="200" />
      </Note>
      <Note Bar="75" BeatPos="8" Track="4" Type="0">
        <ScreenPos x="200" y="-200">
          <FlyTrack name="波浪形" degree="166.6088" />
        </ScreenPos>
      </Note>
      <Note Bar="75" BeatPos="16" Track="4" Type="0">
        <ScreenPos x="200" y="0">
          <FlyTrack name="波浪形" degree="195.5205" />
        </ScreenPos>
      </Note>
      <Note Bar="75" BeatPos="32" Track="4" Type="0">
        <ScreenPos x="-200" y="200">
          <FlyTrack name="波浪形" degree="266.241" />
        </ScreenPos>
      </Note>
      <Note Bar="75" BeatPos="48" Track="4" Type="1" EndBar="76" EndPos="0" ID="50">
        <MoveTrack name="长按直线2" degree="90.33596" />
        <FlyTrack name="波浪形" degree="176.3466" />
        <ScreenPos x="-600" y="200" />
      </Note>
      <Note Bar="76" BeatPos="8" Track="4" Type="0">
        <ScreenPos x="600" y="200">
          <FlyTrack name="波浪形" degree="261.8416" />
        </ScreenPos>
      </Note>
      <Note Bar="76" BeatPos="24" Track="4" Type="0">
        <ScreenPos x="-200" y="-200">
          <FlyTrack name="波浪形" degree="23.64966" />
        </ScreenPos>
      </Note>
      <Note Bar="76" BeatPos="32" Track="4" Type="0">
        <ScreenPos x="-200" y="0">
          <FlyTrack name="波浪形" degree="317.1682" />
        </ScreenPos>
      </Note>
      <Note Bar="76" BeatPos="48" Track="4" Type="0">
        <ScreenPos x="600" y="-200">
          <FlyTrack name="波浪形" degree="84.64059" />
        </ScreenPos>
      </Note>
      <Note Bar="77" BeatPos="0" Track="4" Type="1" EndBar="77" EndPos="16" ID="51">
        <MoveTrack name="长按直线2" degree="359.7026" />
        <FlyTrack name="波浪形" degree="262.8729" />
        <ScreenPos x="-600" y="200" />
      </Note>
      <Note Bar="77" BeatPos="32" Track="4" Type="0">
        <ScreenPos x="600" y="-200">
          <FlyTrack name="波浪形" degree="355.6113" />
        </ScreenPos>
      </Note>
      <Note Bar="77" BeatPos="40" Track="4" Type="0">
        <ScreenPos x="450" y="-50">
          <FlyTrack name="波浪形" degree="345.5901" />
        </ScreenPos>
      </Note>
      <Note Bar="77" BeatPos="48" Track="4" Type="0">
        <ScreenPos x="300" y="100">
          <FlyTrack name="波浪形" degree="344.4847" />
        </ScreenPos>
      </Note>
      <Note Bar="77" BeatPos="56" Track="4" Type="1" EndBar="78" EndPos="8" ID="52">
        <MoveTrack name="长按直线2" degree="0.5144348" />
        <FlyTrack name="波浪形" degree="77.76196" />
        <ScreenPos x="-600" y="-200" />
      </Note>
      <Note Bar="78" BeatPos="24" Track="4" Type="0">
        <ScreenPos x="600" y="200">
          <FlyTrack name="波浪形" degree="293.4234" />
        </ScreenPos>
      </Note>
      <Note Bar="78" BeatPos="32" Track="4" Type="0">
        <ScreenPos x="400" y="200">
          <FlyTrack name="波浪形" degree="241.3256" />
        </ScreenPos>
      </Note>
      <Note Bar="78" BeatPos="48" Track="4" Type="0">
        <ScreenPos x="-600" y="200">
          <FlyTrack name="波浪形" degree="180.0" />
        </ScreenPos>
      </Note>
      <Note Bar="78" BeatPos="56" Track="4" Type="0">
        <ScreenPos x="-450" y="50">
          <FlyTrack name="波浪形" degree="176.0216" />
        </ScreenPos>
      </Note>
      <Note Bar="79" BeatPos="0" Track="4" Type="1" EndBar="79" EndPos="16" ID="53">
        <MoveTrack name="长按直线2" degree="1.939682" />
        <FlyTrack name="波浪形" degree="164.625" />
        <ScreenPos x="-300" y="-100" />
      </Note>
      <Note Bar="79" BeatPos="24" Track="4" Type="0">
        <ScreenPos x="600" y="-200">
          <FlyTrack name="波浪形" degree="68.01498" />
        </ScreenPos>
      </Note>
      <Note Bar="79" BeatPos="32" Track="4" Type="0">
        <ScreenPos x="400" y="-200">
          <FlyTrack name="波浪形" degree="97.32458" />
        </ScreenPos>
      </Note>
      <Note Bar="79" BeatPos="40" Track="4" Type="0">
        <ScreenPos x="-600" y="-200">
          <FlyTrack name="波浪形" degree="165.1188" />
        </ScreenPos>
      </Note>
      <Note Bar="79" BeatPos="48" Track="4" Type="0">
        <ScreenPos x="-600" y="0">
          <FlyTrack name="波浪形" degree="192.8087" />
        </ScreenPos>
      </Note>
      <Note Bar="79" BeatPos="56" Track="4" Type="1" EndBar="80" EndPos="16" ID="54">
        <MoveTrack name="长按直线1.5" degree="180.0" />
        <FlyTrack name="波浪形" degree="263.1788" />
        <ScreenPos x="600" y="200" />
      </Note>
      <Note Bar="80" BeatPos="32" Track="4" Type="0">
        <ScreenPos x="-600" y="-200">
          <FlyTrack name="波浪形" degree="83.4873" />
        </ScreenPos>
      </Note>
      <Note Bar="80" BeatPos="40" Track="4" Type="0">
        <ScreenPos x="-400" y="-200">
          <FlyTrack name="波浪形" degree="87.71286" />
        </ScreenPos>
      </Note>
      <Note Bar="80" BeatPos="48" Track="4" Type="0">
        <ScreenPos x="-200" y="-200">
          <FlyTrack name="波浪形" degree="84.15497" />
        </ScreenPos>
      </Note>
      <Note Bar="80" BeatPos="56" Track="0" Type="2" EndBar="81" EndPos="40" ID="55">
        <MoveTrack name="滑动M型" degree="89.09311" />
        <FlyTrack name="波浪形" degree="84.01874" />
        <ScreenPos x="600" y="-200" />
      </Note>
      <Note Bar="81" BeatPos="56" Track="0" Type="0">
        <ScreenPos x="-600" y="200">
          <FlyTrack name="波浪形" degree="173.9308" />
        </ScreenPos>
      </Note>
      <Note Bar="82" BeatPos="0" Track="0" Type="1" EndBar="82" EndPos="16" ID="56">
        <MoveTrack name="长按直线2" degree="0.0" />
        <FlyTrack name="波浪形" degree="145.3325" />
        <ScreenPos x="-600" y="0" />
      </Note>
      <Note Bar="82" BeatPos="32" Track="0" Type="0">
        <ScreenPos x="600" y="-200">
          <FlyTrack name="波浪形" degree="10.39377" />
        </ScreenPos>
      </Note>
      <Note Bar="82" BeatPos="40" Track="0" Type="0">
        <ScreenPos x="600" y="0">
          <FlyTrack name="波浪形" degree="340.8822" />
        </ScreenPos>
      </Note>
      <Note Bar="82" BeatPos="48" Track="0" Type="0">
        <ScreenPos x="-200" y="200">
          <FlyTrack name="波浪形" degree="290.2631" />
        </ScreenPos>
      </Note>
      <Note Bar="82" BeatPos="56" Track="0" Type="0">
        <ScreenPos x="-400" y="200">
          <FlyTrack name="波浪形" degree="235.5146" />
        </ScreenPos>
      </Note>
      <Note Bar="83" BeatPos="0" Track="0" Type="1" EndBar="83" EndPos="16" ID="57">
        <MoveTrack name="长按直线2" degree="-359.7985" />
        <FlyTrack name="波浪形" degree="81.91791" />
        <ScreenPos x="-600" y="-200" />
      </Note>
      <Note Bar="83" BeatPos="32" Track="0" Type="0">
        <ScreenPos x="600" y="100">
          <FlyTrack name="波浪形" degree="291.5081" />
        </ScreenPos>
      </Note>
      <Note Bar="83" BeatPos="40" Track="0" Type="0">
        <ScreenPos x="400" y="200">
          <FlyTrack name="波浪形" degree="261.3924" />
        </ScreenPos>
      </Note>
      <Note Bar="83" BeatPos="48" Track="0" Type="0">
        <ScreenPos x="200" y="100">
          <FlyTrack name="波浪形" degree="230.8212" />
        </ScreenPos>
      </Note>
      <Note Bar="83" BeatPos="56" Track="0" Type="1" EndBar="84" EndPos="16" ID="58">
        <MoveTrack name="长按直线1.5" degree="0.0" />
        <FlyTrack name="波浪形" degree="87.29771" />
        <ScreenPos x="-600" y="-200" />
      </Note>
      <Note Bar="84" BeatPos="32" Track="0" Type="0">
        <ScreenPos x="600" y="-200">
          <FlyTrack name="波浪形" degree="79.17947" />
        </ScreenPos>
      </Note>
      <Note Bar="84" BeatPos="48" Track="0" Type="0">
        <ScreenPos x="200" y="-200">
          <FlyTrack name="波浪形" degree="175.4739" />
        </ScreenPos>
      </Note>
    </Normal>
  </NoteInfo>
  <ActionSeq type="1">
    <ActionList start_bar="9" dance_len="1" seq_len="4" level="2" type="" />
    <ActionList start_bar="13" dance_len="2" seq_len="4" level="2" type="" />
    <ActionList start_bar="17" dance_len="2" seq_len="4" level="2" type="" />
    <ActionList start_bar="21" dance_len="2" seq_len="4" level="2" type="" />
    <ActionList start_bar="25" dance_len="2" seq_len="2" level="2" type="" />
    <ActionList start_bar="27" dance_len="2" seq_len="8" level="2" type="" />
    <ActionList start_bar="35" dance_len="2" seq_len="8" level="2" type="" />
    <ActionList start_bar="43" dance_len="4" seq_len="4" level="2" type="" />
    <ActionList start_bar="47" dance_len="1" seq_len="4" level="2" type="" />
    <ActionList start_bar="51" dance_len="2" seq_len="4" level="2" type="" />
    <ActionList start_bar="55" dance_len="2" seq_len="4" level="2" type="" />
    <ActionList start_bar="59" dance_len="2" seq_len="4" level="2" type="" />
    <ActionList start_bar="63" dance_len="2" seq_len="2" level="2" type="" />
    <ActionList start_bar="65" dance_len="2" seq_len="8" level="2" type="" />
    <ActionList start_bar="73" dance_len="2" seq_len="4" level="2" type="" />
    <ActionList start_bar="77" dance_len="2" seq_len="4" level="2" type="" />
    <ActionList start_bar="81" dance_len="2" seq_len="4" level="2" type="" />
    <ActionList start_bar="85" dance_len="4" seq_len="4" level="2" type="" />
  </ActionSeq>
  <CameraSeq>
    <Camera name="NL" bar="9" pos="0" end_bar="11" end_pos="0" />
    <Camera name="SR" bar="11" pos="0" end_bar="13" end_pos="0" />
    <Camera name="YAOBI_RL_01" bar="13" pos="0" end_bar="15" end_pos="0" />
    <Camera name="YAOBI_FN_01" bar="15" pos="0" end_bar="17" end_pos="0" />
    <Camera name="SL" bar="17" pos="0" end_bar="19" end_pos="0" />
    <Camera name="YAOBI_NF_03" bar="19" pos="0" end_bar="21" end_pos="0" />
    <Camera name="BL" bar="21" pos="0" end_bar="23" end_pos="0" />
    <Camera name="YAOBI_RL_03" bar="23" pos="0" end_bar="25" end_pos="0" />
    <Camera name="YAOBI_LR_07" bar="25" pos="0" end_bar="27" end_pos="0" />
    <Camera name="YAOBI_RL_06" bar="27" pos="0" end_bar="29" end_pos="0" />
    <Camera name="YAOBI_LR_12" bar="29" pos="0" end_bar="31" end_pos="0" />
    <Camera name="NR" bar="31" pos="0" end_bar="32" end_pos="0" />
    <Camera name="SL" bar="32" pos="0" end_bar="33" end_pos="0" />
    <Camera name="YAOBI_NF_03" bar="33" pos="0" end_bar="35" end_pos="0" />
    <Camera name="YAOBI_LR_13" bar="35" pos="0" end_bar="37" end_pos="0" />
    <Camera name="YAOBI_LR_04" bar="37" pos="0" end_bar="39" end_pos="0" />
    <Camera name="SR" bar="39" pos="0" end_bar="40" end_pos="0" />
    <Camera name="NC" bar="40" pos="0" end_bar="41" end_pos="0" />
    <Camera name="YAOBI_LR_05" bar="41" pos="0" end_bar="43" end_pos="0" />
    <Camera name="NC" bar="43" pos="0" end_bar="47" end_pos="0" />
    <Camera name="SL" bar="47" pos="0" end_bar="49" end_pos="0" />
    <Camera name="NR" bar="49" pos="0" end_bar="51" end_pos="0" />
    <Camera name="YAOBI_RL_02" bar="51" pos="0" end_bar="53" end_pos="0" />
    <Camera name="YAOBI_NF_01" bar="53" pos="0" end_bar="55" end_pos="0" />
    <Camera name="TL" bar="55" pos="0" end_bar="57" end_pos="0" />
    <Camera name="YAOBI_RL_11" bar="57" pos="0" end_bar="59" end_pos="0" />
    <Camera name="BR" bar="59" pos="0" end_bar="61" end_pos="0" />
    <Camera name="YAOBI_NF_02" bar="61" pos="0" end_bar="63" end_pos="0" />
    <Camera name="YAOBI_LR_01" bar="63" pos="0" end_bar="65" end_pos="0" />
    <Camera name="YAOBI_RL_06" bar="65" pos="0" end_bar="67" end_pos="0" />
    <Camera name="YAOBI_LR_03" bar="67" pos="0" end_bar="69" end_pos="0" />
    <Camera name="NC" bar="69" pos="0" end_bar="70" end_pos="0" />
    <Camera name="FC" bar="70" pos="0" end_bar="71" end_pos="0" />
    <Camera name="YAOBI_RL_07" bar="71" pos="0" end_bar="73" end_pos="0" />
    <Camera name="YAOBI_LR_05" bar="73" pos="0" end_bar="75" end_pos="0" />
    <Camera name="YAOBI_RL_12" bar="75" pos="0" end_bar="77" end_pos="0" />
    <Camera name="TL" bar="77" pos="0" end_bar="79" end_pos="0" />
    <Camera name="SR" bar="79" pos="0" end_bar="81" end_pos="0" />
    <Camera name="YAOBI_BF_01" bar="81" pos="0" end_bar="83" end_pos="32" />
    <Camera name="YAOBI_NF_07" bar="83" pos="32" end_bar="85" end_pos="0" />
    <Camera name="NC" bar="85" pos="0" end_bar="89" end_pos="0" />
  </CameraSeq>
  <DancerSort>
    <Bar>15</Bar>
    <Bar>17</Bar>
    <Bar>19</Bar>
    <Bar>21</Bar>
    <Bar>23</Bar>
    <Bar>25</Bar>
    <Bar>27</Bar>
    <Bar>29</Bar>
    <Bar>31</Bar>
    <Bar>33</Bar>
    <Bar>35</Bar>
    <Bar>37</Bar>
    <Bar>39</Bar>
    <Bar>41</Bar>
    <Bar>49</Bar>
    <Bar>50</Bar>
    <Bar>51</Bar>
    <Bar>53</Bar>
    <Bar>55</Bar>
    <Bar>57</Bar>
    <Bar>59</Bar>
    <Bar>61</Bar>
    <Bar>63</Bar>
    <Bar>65</Bar>
    <Bar>67</Bar>
    <Bar>69</Bar>
    <Bar>71</Bar>
    <Bar>73</Bar>
    <Bar>75</Bar>
    <Bar>77</Bar>
    <Bar>79</Bar>
    <Bar>81</Bar>
    <Bar>83</Bar>
  </DancerSort>
  <StageEffectSeq>
    <effect name="wutai_scene_global_script" bar="-1" length="-1" />
    <effect name="wutai_scene_note_biaozhun_01" bar="9" length="34" />
    <effect name="wutai_scene_note_biaozhun_01" bar="47" length="38" />
    <effect name="wutai_scene_note_biaozhun_01" bar="89" length="-1" />
  </StageEffectSeq>
</Level>